abcgan/__init__.py
abcgan/anomaly.py
abcgan/attention.py
abcgan/bv_model.py
abcgan/constants.py
abcgan/evaluate.py
abcgan/hfp_model.py
abcgan/interface.py
abcgan/mask.py
abcgan/mean_estimation.py
abcgan/persist.py
abcgan/tec_model.py
abcgan/transforms.py
abcgan/models/bv_gan.json
abcgan/models/bv_gan.pt
abcgan/models/bv_lidar_gan.json
abcgan/models/bv_lidar_gan.pt
abcgan/models/dr_gan.json
abcgan/models/dr_gan.pt
abcgan/models/hfp_gan.json
abcgan/models/hfp_gan.pt
abcgan/models/wtec_cgan_LSTIDs_MtMoses.json
abcgan/models/wtec_cgan_LSTIDs_MtMoses.pt
abcgan/models/wtec_cgan_LSTIDs_PFRR.json
abcgan/models/wtec_cgan_LSTIDs_PFRR.pt
abcgan/models/wtec_cgan_MSTIDs_MtMoses.json
abcgan/models/wtec_cgan_MSTIDs_MtMoses.pt
abcgan/models/wtec_cgan_MSTIDs_PFRR.json
abcgan/models/wtec_cgan_MSTIDs_PFRR.pt
abcgan/models/wtec_cgan_SSTIDs_ColoradoKCFO.json
abcgan/models/wtec_cgan_SSTIDs_ColoradoKCFO.pt
abcgan/models/wtec_cgan_SSTIDs_HoustonTxSS.json
abcgan/models/wtec_cgan_SSTIDs_HoustonTxSS.pt
abcgan/models/wtec_cgan_SSTIDs_MidlandTxSS.json
abcgan/models/wtec_cgan_SSTIDs_MidlandTxSS.pt
abcgan/models/wtec_cgan_SSTIDs_NMexicoSPA.json
abcgan/models/wtec_cgan_SSTIDs_NMexicoSPA.pt
abcgan/models/wtec_cgan_SSTIDs_OklahomaCSM.json
abcgan/models/wtec_cgan_SSTIDs_OklahomaCSM.pt
abcgan/models/wtec_cgan_SSTIDs_PFRR.json
abcgan/models/wtec_cgan_SSTIDs_PFRR.pt
abcgan/models/wtec_cgan_SSTIDs_SouthWest.json
abcgan/models/wtec_cgan_SSTIDs_SouthWest.pt
abcgan/models/wtec_cgan_TSTIDs_ColoradoKCFO.json
abcgan/models/wtec_cgan_TSTIDs_ColoradoKCFO.pt
abcgan/models/wtec_cgan_TSTIDs_HoustonTxSS.json
abcgan/models/wtec_cgan_TSTIDs_HoustonTxSS.pt
abcgan/models/wtec_cgan_TSTIDs_MidlandTxSS.json
abcgan/models/wtec_cgan_TSTIDs_MidlandTxSS.pt
abcgan/models/wtec_cgan_TSTIDs_NMexicoSPA.json
abcgan/models/wtec_cgan_TSTIDs_NMexicoSPA.pt
abcgan/models/wtec_cgan_TSTIDs_OklahomaCSM.json
abcgan/models/wtec_cgan_TSTIDs_OklahomaCSM.pt
abcgan/models/wtec_cgan_TSTIDs_PFRR.json
abcgan/models/wtec_cgan_TSTIDs_PFRR.pt
abcgan-4.0.0.dist-info/LICENSE.txt
abcgan-4.0.0.dist-info/METADATA
abcgan-4.0.0.dist-info/WHEEL
abcgan-4.0.0.dist-info/top_level.txt
abcgan-4.0.0.dist-info/RECORD
