Metadata-Version: 2.1
Name: abcgan
Version: 4.0.0
Summary: Generator and Discriminator for Atmosense Background Characterization
Home-page: https://github.com/sri-geospace/atmosense-abcgan
Author: SRI International
Author-email: andrew.silberfarb@sri.com
License: MIT
Project-URL: Source Code, https://github.com/sri-geospace/atmosense-abcgan/
Project-URL: Issue Tracker, https://github.com/sri-geospace/atmosense-abcgan/issues
Project-URL: Documentation, https://atmosense-abcgan.readthedocs.io/en/latest/
Project-URL: Binder, https://mybinder.org/v2/gh/sri-geospace/atmosense-abcgan/HEAD?labpath=tutorials%2Fdemo.ipynb
Classifier: Programming Language :: Python :: 3
Classifier: License :: OSI Approved :: MIT License
Classifier: Operating System :: OS Independent
Requires-Python: >=3.8
License-File: LICENSE.txt
Requires-Dist: scipy (>=1.2)
Requires-Dist: numpy
Requires-Dist: torch
Requires-Dist: pandas (>=0.24.0)
Requires-Dist: h5py
Requires-Dist: tqdm
Requires-Dist: requests
